dushizhenMath2/__init__.py
dushizhenMath2/demo1.py
dushizhenMath2/demo2.py
dushizhenMath2-1.0.dist-info/METADATA
dushizhenMath2-1.0.dist-info/WHEEL
dushizhenMath2-1.0.dist-info/top_level.txt
dushizhenMath2-1.0.dist-info/RECORD
